fifo/gray_fifo.v
module gray_fifo #(
    parameter DATA_WIDTH = 8,
    parameter ADDR_WIDTH = 4
)(
    input  wire wr_clk,
    input  wire rd_clk,
    input  wire rst,
    input  wire wr_en,
    input  wire rd_en,
    input  wire [DATA_WIDTH-1:0] din,
    output reg  [DATA_WIDTH-1:0] dout,
    output wire full,
    output wire empty
);

    localparam DEPTH = 1 << ADDR_WIDTH;

    reg [DATA_WIDTH-1:0] mem [0:DEPTH-1];

    // Binary pointers
    reg [ADDR_WIDTH:0] wr_ptr_bin = 0;
    reg [ADDR_WIDTH:0] rd_ptr_bin = 0;

    // Gray pointers
    wire [ADDR_WIDTH:0] wr_ptr_gray;
    wire [ADDR_WIDTH:0] rd_ptr_gray;

    assign wr_ptr_gray = wr_ptr_bin ^ (wr_ptr_bin >> 1);
    assign rd_ptr_gray = rd_ptr_bin ^ (rd_ptr_bin >> 1);

    // Write logic
    always @(posedge wr_clk or posedge rst) begin
        if (rst)
            wr_ptr_bin <= 0;
        else if (wr_en && !full) begin
            mem[wr_ptr_bin[ADDR_WIDTH-1:0]] <= din;
            wr_ptr_bin <= wr_ptr_bin + 1;
        end
    end

    // Read logic
    always @(posedge rd_clk or posedge rst) begin
        if (rst) begin
            rd_ptr_bin <= 0;
            dout <= 0;
        end else if (rd_en && !empty) begin
            dout <= mem[rd_ptr_bin[ADDR_WIDTH-1:0]];
            rd_ptr_bin <= rd_ptr_bin + 1;
        end
    end

    // Empty and Full logic using Gray codes
    assign empty = (wr_ptr_gray == rd_ptr_gray);
    assign full = (wr_ptr_gray == {~rd_ptr_gray[ADDR_WIDTH:ADDR_WIDTH-1], rd_ptr_gray[ADDR_WIDTH-2:0]});

endmodule

fifo/gray_fifo_tb.v
module gray_fifo_tb;

    reg clk_wr = 0, clk_rd = 0, rst = 1;
    reg wr_en = 0, rd_en = 0;
    reg [7:0] din = 0;
    wire [7:0] dout;
    wire full, empty;

    gray_fifo dut (
        .wr_clk(clk_wr),
        .rd_clk(clk_rd),
        .rst(rst),
        .wr_en(wr_en),
        .rd_en(rd_en),
        .din(din),
        .dout(dout),
        .full(full),
        .empty(empty)
    );

    // Write and read clocks
    always #5 clk_wr = ~clk_wr;
    always #7 clk_rd = ~clk_rd;

    initial begin
        $dumpfile("gray_fifo_tb.vcd");
        $dumpvars(0, gray_fifo_tb);

        #10 rst = 0;

        // Write 10 values
        repeat(10) begin
            @(posedge clk_wr);
            if (!full) begin
                wr_en <= 1;
                din <= din + 1;
            end
        end
        wr_en <= 0;

        // Delay before reading
        #50;

        // Read 10 values
        repeat(10) begin
            @(posedge clk_rd);
            if (!empty)
                rd_en <= 1;
        end
        rd_en <= 0;

        #50 $finish;
    end

endmodule

fifo/gray_fifo_tb.vcd
$date
	Thu Jul 10 21:52:50 2025
$end
$version
	Icarus Verilog
$end
$timescale
	1s
$end
$scope module gray_fifo_tb $end
$var wire 1 ! full $end
$var wire 1 " empty $end
$var wire 8 # dout [7:0] $end
$var reg 1 $ clk_rd $end
$var reg 1 % clk_wr $end
$var reg 8 & din [7:0] $end
$var reg 1 ' rd_en $end
$var reg 1 ( rst $end
$var reg 1 ) wr_en $end
$scope module dut $end
$var wire 8 * din [7:0] $end
$var wire 1 $ rd_clk $end
$var wire 1 ' rd_en $end
$var wire 5 + rd_ptr_gray [4:0] $end
$var wire 1 ( rst $end
$var wire 1 % wr_clk $end
$var wire 1 ) wr_en $end
$var wire 5 , wr_ptr_gray [4:0] $end
$var wire 1 ! full $end
$var wire 1 " empty $end
$var parameter 32 - ADDR_WIDTH $end
$var parameter 32 . DATA_WIDTH $end
$var parameter 36 / DEPTH $end
$var reg 8 0 dout [7:0] $end
$var reg 5 1 rd_ptr_bin [4:0] $end
$var reg 5 2 wr_ptr_bin [4:0] $end
$upscope $end
$upscope $end
$enddefinitions $end
$comment Show the parameter values. $end
$dumpall
b10000 /
b1000 .
b100 -
$end
#0
$dumpvars
b0 2
b0 1
b0 0
b0 ,
b0 +
b0 *
0)
1(
0'
b0 &
0%
0$
b0 #
1"
0!
$end
#5
1%
#7
1$
#10
0%
0(
#14
0$
#15
b1 &
b1 *
1)
1%
#20
0%
#21
1$
#25
0"
b1 ,
b1 2
b10 &
b10 *
1%
#28
0$
#30
0%
#35
b11 ,
b10 2
b11 &
b11 *
1%
1$
#40
0%
#42
0$
#45
b10 ,
b11 2
b100 &
b100 *
1%
#49
1$
#50
0%
#55
b110 ,
b100 2
b101 &
b101 *
1%
#56
0$
#60
0%
#63
1$
#65
b111 ,
b101 2
b110 &
b110 *
1%
#70
0%
0$
#75
b101 ,
b110 2
b111 &
b111 *
1%
#77
1$
#80
0%
#84
0$
#85
b100 ,
b111 2
b1000 &
b1000 *
1%
#90
0%
#91
1$
#95
b1100 ,
b1000 2
b1001 &
b1001 *
1%
#98
0$
#100
0%
#105
b1101 ,
b1001 2
0)
b1010 &
b1010 *
1%
1$
#110
0%
#112
0$
#115
1%
#119
1$
#120
0%
#125
1%
#126
0$
#130
0%
#133
1$
#135
1%
#140
0%
0$
#145
1%
#147
1$
#150
0%
#154
0$
#155
1%
#160
0%
#161
1'
1$
#165
1%
#168
0$
#170
0%
#175
b1 +
b1 1
b1 #
b1 0
1%
1$
#180
0%
#182
0$
#185
1%
#189
b11 +
b10 1
b10 #
b10 0
1$
#190
0%
#195
1%
#196
0$
#200
0%
#203
b10 +
b11 1
b11 #
b11 0
1$
#205
1%
#210
0%
0$
#215
1%
#217
b110 +
b100 1
b100 #
b100 0
1$
#220
0%
#224
0$
#225
1%
#230
0%
#231
b111 +
b101 1
b101 #
b101 0
1$
#235
1%
#238
0$
#240
0%
#245
b101 +
b110 1
b110 #
b110 0
1%
1$
#250
0%
#252
0$
#255
1%
#259
b100 +
b111 1
b111 #
b111 0
1$
#260
0%
#265
1%
#266
0$
#270
0%
#273
b1100 +
b1000 1
b1000 #
b1000 0
1$
#275
1%
#280
0%
0$
#285
1%
#287
1"
b1101 +
b1001 1
b1001 #
b1001 0
0'
1$
